recov/__init__.py
recov/py.typed
recov-0.3.0.dist-info/METADATA
recov-0.3.0.dist-info/WHEEL
recov-0.3.0.dist-info/entry_points.txt
recov-0.3.0.dist-info/licenses/LICENSE
recov-0.3.0.dist-info/RECORD
