Metadata-Version: 2.4
Name: recov
Version: 0.3.0
Summary: Analyze test redundancy using coverage data.
Project-URL: Homepage, https://github.com/jirikuncar/recov
Project-URL: Documentation, https://github.com/jirikuncar/recov#readme
Project-URL: Repository, https://github.com/jirikuncar/recov
Project-URL: Changelog, https://github.com/jirikuncar/recov/releases
Project-URL: Issues, https://github.com/jirikuncar/recov/issues
Author-email: Jiri Kuncar <jiri.kuncar@gmail.com>
License: MIT License
License-File: LICENSE
Keywords: coverage,static-analysis,test
Classifier: Development Status :: 3 - Alpha
Classifier: Intended Audience :: Developers
Classifier: License :: OSI Approved :: MIT License
Classifier: Programming Language :: Python :: 3
Classifier: Programming Language :: Python :: 3.12
Classifier: Programming Language :: Python :: 3.13
Classifier: Programming Language :: Python :: 3.14
Classifier: Programming Language :: SQL
Classifier: Topic :: Software Development :: Libraries :: Python Modules
Classifier: Topic :: Software Development :: Testing
Classifier: Topic :: Utilities
Classifier: Typing :: Typed
Requires-Python: >=3.12
Requires-Dist: coverage
Requires-Dist: rich
